cord/__init__.py
cord/default.conf.template
cord/modelrun.py
cord/ripcas_dflow.py
cord/veg2npol.py
cord/data/peak.txt
cord/data/shear_out.asc
cord/data/dflow_inputs/DBC_geometry.xyz
cord/data/dflow_inputs/base.ext
cord/data/dflow_inputs/base.mdu
cord/data/dflow_inputs/base_net.nc
cord/data/dflow_inputs/boundriver_up.pli
cord/data/dflow_inputs/boundriverdown.pli
cord/data/dflow_inputs/dflow_mpi.pbs
cord/data/ripcas_inputs/veg_roughness_shearres.xlsx
cord/data/ripcas_inputs/vegclass_2z.asc
cord/data/ripcas_inputs/zonemap_2z.asc
cord/data/ripcas_inputs/~$ripcas-data-requirements.xlsx
cord/scripts/__init__.py
cord/scripts/cord.py
cord-0.2.4.dist-info/DESCRIPTION.rst
cord-0.2.4.dist-info/METADATA
cord-0.2.4.dist-info/RECORD
cord-0.2.4.dist-info/WHEEL
cord-0.2.4.dist-info/entry_points.txt
cord-0.2.4.dist-info/metadata.json
cord-0.2.4.dist-info/top_level.txt
test/__init__.py
test/test_cord.py
