Metadata-Version: 2.0
Name: cord
Version: 0.2.4
Summary: Coupled RipCAS-DFLOW for Vegetation and Hydrology of Streams
Home-page: UNKNOWN
Author: Matthew Turner
Author-email: maturner01@gmail.com
License: BSD3
Platform: UNKNOWN
Classifier: License :: OSI Approved :: BSD License
Classifier: Programming Language :: Python :: 2.7
Classifier: Environment :: Console
Classifier: Development Status :: 4 - Beta
Classifier: Topic :: Scientific/Engineering
Classifier: Intended Audience :: Science/Research
Requires-Dist: Cython (>=0.24)
Requires-Dist: backports.shutil-get-terminal-size (>=1.0.0)
Requires-Dist: click (>=6.6)
Requires-Dist: configparser (>=3.3.0.post2)
Requires-Dist: cookies (>=2.2.1)
Requires-Dist: decorator (>=4.0.9)
Requires-Dist: funcsigs (>=1.0.2)
Requires-Dist: gnureadline (>=6.3.3)
Requires-Dist: h5py (>=2.5.0)
Requires-Dist: hs-restclient (>=1.2.2)
Requires-Dist: netCDF4 (>=1.2.3.1)
Requires-Dist: nose (>=1.3.7)
Requires-Dist: numpy (==1.11.0)
Requires-Dist: oauthlib (>=1.1.1)
Requires-Dist: pandas (>=0.17.1)
Requires-Dist: pathlib2 (>=2.1.0)
Requires-Dist: pbr (>=1.9.1)
Requires-Dist: pexpect (>=4.0.1)
Requires-Dist: pickleshare (>=0.7.2)
Requires-Dist: ptyprocess (>=0.5.1)
Requires-Dist: python-dateutil (>=2.5.0)
Requires-Dist: pytz (>=2015.7)
Requires-Dist: requests (>=2.10.0)
Requires-Dist: requests-oauthlib (>=0.6.1)
Requires-Dist: requests-toolbelt (>=0.6.0)
Requires-Dist: scipy (==0.17.0)
Requires-Dist: simplegeneric (>=0.8.1)
Requires-Dist: six (>=1.10.0)
Requires-Dist: traitlets (>=4.2.1)
Requires-Dist: xlrd (>=0.9.4)
